setup.py
ucmclient/__init__.py
ucmclient/examples.py
ucmclient/ucmclient.py
ucmclient.egg-info/PKG-INFO
ucmclient.egg-info/SOURCES.txt
ucmclient.egg-info/dependency_links.txt
ucmclient.egg-info/not-zip-safe
ucmclient.egg-info/requires.txt
ucmclient.egg-info/top_level.txt