Metadata-Version: 1.0
Name: ucmclient
Version: 0.1.0
Summary: A python client for communicating with Oracle UCM 11g Content Server
Home-page: http://www.webmasterwords.com/python-ucm-client
Author: stuart robinson
Author-email: webmasterwords+pypi@gmail.com
License: UNKNOWN
Keywords: oracle ucm services client
Platform: UNKNOWN
Classifier: Intended Audience :: Developers
Classifier: License :: OSI Approved :: GNU General Public License (GPL)
Classifier: Natural Language :: English
Classifier: Programming Language :: Python :: 2.7
Classifier: Topic :: Internet :: WWW/HTTP
